{"name": "Baccarat Rouge 540 Extrait de Parfum Maison Francis Kurkdjian", "brand": "Maison Francis Kurkdjian", "gender": "women and men", "accords": ["amber", "almond", "warm spicy", "woody", "musky", "animalic", "nutty", "fruity", "white floral", "metallic"], "ideal_times": {"winter": "100%", "spring": "66.2523%", "summer": "35.6902%", "fall": "97.7985%", "day": "70.1632%", "night": "95.7265%"}, "notes": {"top_notes": ["Bitter Almond", "Saffron"], "middle_notes": ["Egyptian Jasmine", "Virginia Cedar"], "base_notes": ["Ambergris", "Woody Notes", "Musk", "Ambroxan", "Cashmeran"]}, "img_url": "https://fimgs.net/mdimg/perfume-thumbs/375x500.46066.jpg"}